{"is_source_file": true, "format": "TypeScript/TSX", "description": "React component for a password reset route, handling user input for new password and interaction with AuthAPI to reset password using a token from URL search parameters.", "external_files": ["~/utils/api", "~/components/Forms"], "external_methods": ["AuthAPI.reset", "useSearchParams", "useState", "FormEvent", "setTimeout", "window.location.href"], "published": [], "classes": [], "methods": [{"name": "ResetPasswordRoute", "description": "Main React component for resetting password, managing form state, handling submission, and rendering UI."}], "calls": ["AuthAPI.reset", "useSearchParams", "useState", "setError", "setOk", "setTimeout", "window.location.href"], "search-terms": ["ResetPasswordRoute", "reset password", "token from URL", "useSearchParams", "AuthAPI", "password reset form", "react component"], "state": 2, "file_id": 23, "knowledge_revision": 60, "git_revision": "", "revision_history": [{"50": ""}, {"60": ""}], "ctags": [], "hash": "51d79463663521465e51330c63635972", "format-version": 4, "code-base-name": "meeting_app_frontend", "filename": "meeting_app_frontend/app/routes/reset-password.tsx"}